cyberpulse/__init__.py
cyberpulse/cli.py
cyberpulse/cloud.py
cyberpulse/config.py
cyberpulse/db.py
cyberpulse/local_llm.py
cyberpulse/models.py
cyberpulse/notifier.py
cyberpulse/parsers.py
cyberpulse/rules.py
cyberpulse/summarizer.py
cyberpulse-0.1.3.dist-info/METADATA
cyberpulse-0.1.3.dist-info/WHEEL
cyberpulse-0.1.3.dist-info/entry_points.txt
cyberpulse-0.1.3.dist-info/top_level.txt
cyberpulse-0.1.3.dist-info/RECORD
