Metadata-Version: 2.4
Name: cyberpulse
Version: 0.1.3
Summary: Risk-based vulnerability fix list generator
Home-page: https://github.com/yourusername/cyberpulse
Author: Jason Wexler
Author-email: Your Name <you@example.com>
Requires-Python: >=3.8
Requires-Dist: click>=8
Requires-Dist: sqlalchemy>=2
Requires-Dist: llama-cpp-python>=0.2.86
Requires-Dist: PyYAML>=6.0
Provides-Extra: server
Requires-Dist: llama-cpp-python[server]>=0.2.86; extra == "server"
Dynamic: author
Dynamic: home-page
Dynamic: requires-python
